cpu.v
/*
module top(
    input CLK,
    output RED1,
    output RED2,
    output RED3,
    output RED4,
    output GREEN
);

assign {RED1, RED2, RED3, RED4, GREEN} = b_out[4:0];
*/

module cpu(input CLK);
assign clk = CLK;

reg[15:0] bus;
always @(*) begin
    if (a_en) begin
        bus = a_out;
    end else if (b_en) begin
        bus = b_out;
    end else if (alu_en) begin
        bus = alu_out;
    end else if (ram_en | stack_en) begin
        bus = ram_out;
    end else if (pc_en) begin
        bus = pc_out;
    end else if (ir_en) begin
        bus = ir_out;
    end else begin
        bus = 16'b0;
    end
end
/*
wire clk;
clock clock(
    .clk_in(CLK),
    .clk_out(clk)
);
*/
localparam FLAG_C = 1;
wire[2:0] alu_op;
wire alu_en;
wire[15:0] alu_out;
wire alu_c_flag;
alu alu(
    .clk(clk),
    .a(a_out),
    .b(b_out),
    .alu_op(alu_op),
    .out(alu_out),
    .flag_c_in(flags[FLAG_C]),
    .flag_c_out(alu_c_flag)
);

wire[2:0] flags;
flag_mux flag_mux(
    .clk(clk),
    .a_out(a_out),
    .alu_op(alu_op != 0),
    .a_load(a_load),
    .a_op(a_op != 0),
    .alu_c_flag(alu_c_flag),
    .a_c_flag(a_c_flag),
    .out(flags)
);

wire ram_en;
wire mar_load;
wire ram_load;
wire stack_load;
wire stack_en;
wire[15:0] ram_out;
ram ram(
    .clk(clk),
    .ram_en(ram_en),
    .mar_load(mar_load),
    .ram_load(ram_load),
    .stack_load(stack_load),
    .stack_en(stack_en),
    .ir_arg(ir_out[9:0]),
    .sp_out(sp_out),
    .bus(bus),
    .out(ram_out)
);

controller controller(
    .clk(clk),
    .ir_opcode(ir_out[15:12]),
    .ram_opcode(ram_out[15:12]),
    .ram_arg(ram_out[11:0]),
    .stack_opcode(ir_out[11:10]),
    .flags(flags),
    .alu_op(alu_op),
    .a_op(a_op),
    .out({
        stack_load,
        stack_en,
        sp_add,
        alu_en,
        ram_en,
        mar_load,
        ram_load,
        a_en,
        a_load,
        b_en,
        b_load,
        pc_en,
        pc_load,
        pc_inc,
        ir_en,
        ir_load
    })
);

wire[2:0] a_op;
wire a_en;
wire a_load;
wire[15:0] a_out;
wire a_c_flag;
a reg_a(
    .clk(clk),
    .load(a_load),
    .a_op(a_op),
    .bus(bus),
    .out(a_out),
    .flag_c_in(flags[FLAG_C]),
    .flag_c_out(a_c_flag)
);

wire b_en;
wire b_load;
wire[15:0] b_out;
register reg_b(
    .clk(clk),
    .load(b_load),
    .bus(bus),
    .out(b_out)
);

wire ir_en;
wire ir_load;
wire[15:0] ir_out;
register ir(
    .clk(clk),
    .load(ir_load),
    .bus(bus),
    .out(ir_out)
);

wire pc_en;
wire pc_load;
wire pc_inc;
wire[15:0] pc_out;
pc pc(
    .clk(clk),
    .load(pc_load),
    .inc(pc_inc),
    .bus(bus[11:0]),
    .out(pc_out)
);

wire sp_add;
wire[15:0] sp_out;
sp sp(
    .clk(clk),
    .stack_load(stack_load),
    .sp_add(sp_add),
    .ram_arg(ram_out[9:0]),
    .out(sp_out)
);

endmodule

module clock(
    input clk_in,
    output clk_out
);

reg [22:0] counter;
reg [5:0] delay;
reg clk_out;

always @(posedge clk_in) begin
  if (delay < 63) begin
    delay <= delay + 1;
  end else begin
    counter <= counter + 1;
    clk_out <= counter[1];//change number to change clock speed
  end
end

endmodule

module ram(
	input clk,
	input ram_en,
	input mar_load,
	input ram_load,
    input stack_load,
    input stack_en,
    input[9:0] ir_arg,
    input[15:0] sp_out,
	input[15:0] bus,
	output[15:0] out
);

/*
NOARG 	0000ffffffffffff
LOADA 	0001ffffffffffff
STORE 	0010ffffffffffff
ADD 	0011ffffffffffff
ADDC 	0100ffffffffffff
SUB 	0101ffffffffffff
SUBB 	0110ffffffffffff
MOD 	0111ffffffffffff
AND 	1000ffffffffffff
OR 		1001ffffffffffff
XOR 	1010ffffffffffff
JMP 	1011ffffffffffff
JMPZ 	1100ffffffffffff
JMPC 	1101ffffffffffff
JMPS 	1110ffffffffffff
CALL 	1111ffffffffffff

LDSTA   000001ffffffffff
POP     000010ffffffffff
RET     000011ffffffffff

NOOP 	0000000000000000
INC 	0000000000000001
DEC 	0000000000000010
SHL 	0000000000000011
SHR 	0000000000000100
NOT 	0000000000000101
COM 	0000000000000110
PUSH 	0000000000000111

*/

reg[11:0] mar;
reg[15:0] ram[0:12'b111111111111];

integer i;
initial begin
    mar = 12'b0;

	for (i = 0; i < 13'b1000000000000; i = i + 1) begin
		ram[i] = 16'b0000000000000000;
	end
    /*
    ram[0]  = 16'b0001000000001101;//load mem1
    ram[1]  = 16'b0011000000001110;//add mem2
    ram[2]  = 16'b0010000000001111;//store mem3
    ram[3]  = 16'b0001000000000000;//load 0
    ram[4]  = 16'b0000000000000001;//inc
    ram[5]  = 16'b0010000000000000;//store 0
    ram[6]  = 16'b0001000000000001;//load 1
    ram[7]  = 16'b0000000000000001;//inc
    ram[8]  = 16'b0010000000000001;//store
    ram[9]  = 16'b0001000000000010;//load 2
    ram[10] = 16'b0000000000000001;//inc
    ram[11] = 16'b0010000000000010;//store 2
    ram[12] = 16'b1011000000000000;//jump 0
    ram[13] = 16'b0000000000000001;
    ram[14] = 16'b0000000000000001;
    */
    /*
    ram[0] = 16'b1111000000000010;//call 2
    ram[1] = 16'b1011000000000000;//jump 0
    ram[2] = 16'b0000000000000001;//inc
    ram[3] = 16'b0000110000000000;//ret 0
    */
    /*
    ram[0] = 16'b0000000000000001;//inc
    ram[1] = 16'b0000000000000111;//push
    ram[2] = 16'b0000000000000010;//dec
    ram[3] = 16'b0000100000000000;//pop 0
    */
    /*
    ram[0] = 16'b0000000000000001;//inc
    ram[1] = 16'b0000000000000111;//push
    ram[2] = 16'b0000000000000001;//inc
    ram[3] = 16'b0000000000000111;//push
    ram[4] = 16'b0000100000000000;//pop 0
    ram[5] = 16'b0000100000000000;//pop 0
    */
    

end

wire[16:0] top;
assign top = ram[sp_out];

reg[15:0] out;
always @(posedge clk) begin
	if (ram_en) begin
		out <= ram[mar];
	end else if (mar_load) begin
		mar <= bus[11:0];
	end else if (ram_load) begin
		ram[mar] <= bus;
    end else if (stack_load) begin
        ram[sp_out] <= bus;
    end else if (stack_en) begin
        out <= ram[sp_out + ir_arg + 1];
    end
end

endmodule

module controller(
    input clk,
    input[3:0] ir_opcode,
    input[3:0] ram_opcode,
    input[11:0] ram_arg,
    input[1:0] stack_opcode,//from ir
    input[2:0] flags,
    output[2:0] alu_op,
    output[2:0] a_op,
    output[15:0] out
);

//opcodes
localparam OP_NOARG = 4'b0000;
localparam OP_LOADA = 4'b0001;
localparam OP_STORE = 4'b0010;
localparam OP_ADD   = 4'b0011;
localparam OP_ADDC  = 4'b0100;
localparam OP_SUB   = 4'b0101;
localparam OP_SUBB  = 4'b0110;
localparam OP_MOD   = 4'b0111;
localparam OP_AND   = 4'b1000;
localparam OP_OR    = 4'b1001;
localparam OP_XOR   = 4'b1010;
localparam OP_JMP   = 4'b1011;
localparam OP_JMPZ  = 4'b1100;
localparam OP_JMPC  = 4'b1101;
localparam OP_JMPS  = 4'b1110;
localparam OP_CALL  = 4'b1111;

localparam OP_NOST  = 2'b00;
localparam OP_LDSTA = 2'b01;
localparam OP_POP   = 2'b10;
localparam OP_RET   = 2'b11;

localparam OP_NOOP  = 12'b000000000000;
localparam OP_INC   = 12'b000000000001;
localparam OP_DEC   = 12'b000000000010;
localparam OP_SHL   = 12'b000000000011;
localparam OP_SHR   = 12'b000000000100;
localparam OP_NOT   = 12'b000000000101;
localparam OP_COM   = 12'b000000000110;
localparam OP_PUSH  = 12'b000000000111;

//signals
localparam SIG_STACK_LOAD = 15;
localparam SIG_STACK_EN =   14;
localparam SIG_SP_ADD =     13;
localparam SIG_ALU_EN =     12;
localparam SIG_RAM_EN =     11;
localparam SIG_MAR_LOAD =   10;
localparam SIG_RAM_LOAD =   9;
localparam SIG_A_EN =       8;
localparam SIG_A_LOAD =     7;
localparam SIG_B_EN =       6;
localparam SIG_B_LOAD =     5;
localparam SIG_PC_EN =      4;
localparam SIG_PC_LOAD =    3;
localparam SIG_PC_INC =     2;
localparam SIG_IR_EN =      1;
localparam SIG_IR_LOAD =    0;

//alu ops
localparam ALU_ADD = 0;
localparam ALU_ADDC = 1;
localparam ALU_SUB = 2;
localparam ALU_SUBB = 3;
localparam ALU_MOD = 4;
localparam ALU_AND = 5;
localparam ALU_OR = 6;
localparam ALU_XOR = 7;

//a ops
localparam A_INC = 1;
localparam A_DEC = 2;
localparam A_SHL = 3;
localparam A_SHR = 4;
localparam A_NOT = 5;
localparam A_COM = 6;

//flags
localparam FLAG_Z = 0;
localparam FLAG_C = 1;
localparam FLAG_S = 2;


reg[2:0] stage;
reg[15:0] ctrl_word;
reg[2:0] alu_op;
reg[2:0] a_op;
reg stage_rst;
wire[3:0] ir_opcode;
wire[3:0] ram_opcode;
wire[11:0] ram_arg;
wire[1:0] stack_opcode;
wire[1:0] ram_stack_opcode;

assign ram_stack_opcode = ram_arg[11:10];

always @(negedge clk) begin
    if (stage_rst) begin
        stage <= 0;
    end else begin
        stage <= stage + 1;
    end
end

initial begin
    stage <= 0;
end

always @(*) begin
    ctrl_word = 0;
    alu_op = 0;
    a_op = 0;
    stage_rst = 0;
    case (stage)
        0: begin
            ctrl_word[SIG_PC_EN] = 1;
            ctrl_word[SIG_MAR_LOAD] = 1;
        end
        1: begin
            ctrl_word[SIG_RAM_EN] = 1;
            ctrl_word[SIG_IR_LOAD] = 1;
            case (ram_opcode)
                OP_NOARG: begin
                    ctrl_word[SIG_PC_INC] = 1;
                    case (ram_arg)
                        OP_NOOP: begin
                            stage_rst = 1;
                        end
                        OP_INC: begin
                            a_op = A_INC;
                            stage_rst = 1;
                        end
                        OP_DEC: begin
                            a_op = A_DEC;
                            stage_rst = 1;
                        end
                        OP_SHL: begin
                            a_op = A_SHL;
                            stage_rst = 1;
                        end
                        OP_SHR: begin
                            a_op = A_SHR;
                            stage_rst = 1;
                        end
                        OP_NOT: begin
                            a_op = A_NOT;
                            stage_rst = 1;
                        end
                        OP_COM: begin
                            a_op = A_COM;
                            stage_rst = 1;
                        end
                    endcase
                end
                OP_JMP: begin
                    ctrl_word[SIG_PC_LOAD] = 1;
                    stage_rst = 1;
                end
                OP_JMPZ: begin
                    if (flags[FLAG_Z]) begin
                        ctrl_word[SIG_PC_LOAD] = 1;
                    end else begin
                        ctrl_word[SIG_PC_INC] = 1;
                    end
                    stage_rst = 1;
                end
                OP_JMPC: begin
                    if (flags[FLAG_C]) begin
                        ctrl_word[SIG_PC_LOAD] = 1;
                    end else begin
                        ctrl_word[SIG_PC_INC] = 1;
                    end
                    stage_rst = 1;
                end
                OP_JMPS: begin
                    if (flags[FLAG_S]) begin
                        ctrl_word[SIG_PC_LOAD] = 1;
                    end else begin
                        ctrl_word[SIG_PC_INC] = 1;
                    end
                    stage_rst = 1;
                end
                default: begin
                    ctrl_word[SIG_PC_INC] = 1;
                end      
            endcase
        end
        2: begin
            if (ram_opcode == OP_CALL) begin
                ctrl_word[SIG_RAM_EN] = 1;
                ctrl_word[SIG_STACK_LOAD] = 1;
                ctrl_word[SIG_PC_LOAD] = 1;
                stage_rst = 1;
            end else if (ram_opcode != 0) begin
                ctrl_word[SIG_IR_EN] = 1;
                ctrl_word[SIG_MAR_LOAD] = 1;
            end else begin
                stage_rst = 1;
                case (stack_opcode)
                    OP_NOST: begin
                        ctrl_word[SIG_A_EN] = 1;
                        ctrl_word[SIG_STACK_LOAD] = 1;
                    end
                    OP_LDSTA: begin
                        ctrl_word[SIG_STACK_EN] = 1;
                        ctrl_word[SIG_A_LOAD] = 1;
                    end
                    OP_POP: begin
                        ctrl_word[SIG_STACK_EN] = 1;
                        ctrl_word[SIG_A_LOAD] = 1;
                        ctrl_word[SIG_SP_ADD] = 1;
                    end
                    OP_RET: begin
                        ctrl_word[SIG_STACK_EN] = 1;
                        ctrl_word[SIG_PC_LOAD] = 1;
                        ctrl_word[SIG_SP_ADD] = 1;
                    end
                endcase
            end
        end
        3: begin
            case (ir_opcode)
                OP_LOADA: begin
                    ctrl_word[SIG_RAM_EN] = 1;
                    ctrl_word[SIG_A_LOAD] = 1;
                    stage_rst = 1;
                end
                OP_STORE: begin
                    ctrl_word[SIG_A_EN] = 1;
                    ctrl_word[SIG_RAM_LOAD] = 1;
                    stage_rst = 1;
                end
                default: begin
                    ctrl_word[SIG_RAM_EN] = 1;
                    ctrl_word[SIG_B_LOAD] = 1;
                end
            endcase
        end
        4: begin
            case (ir_opcode)
                OP_ADD: begin
                    alu_op = ALU_ADD;
                    ctrl_word[SIG_ALU_EN] = 1;
                    ctrl_word[SIG_A_LOAD] = 1;
                    stage_rst = 1;
                end
                OP_ADDC: begin
                    alu_op = ALU_ADDC;
                    ctrl_word[SIG_ALU_EN] = 1;
                    ctrl_word[SIG_A_LOAD] = 1;
                    stage_rst = 1;
                end
                OP_SUB: begin
                    alu_op = ALU_SUB;
                    ctrl_word[SIG_ALU_EN] = 1;
                    ctrl_word[SIG_A_LOAD] = 1;
                    stage_rst = 1;
                end
                OP_SUBB: begin
                    alu_op = ALU_SUBB;
                    ctrl_word[SIG_ALU_EN] = 1;
                    ctrl_word[SIG_A_LOAD] = 1;
                    stage_rst = 1;
                end
                OP_MOD: begin
                    alu_op = ALU_MOD;
                    ctrl_word[SIG_ALU_EN] = 1;
                    ctrl_word[SIG_A_LOAD] = 1;
                    stage_rst = 1;
                end
                OP_AND: begin
                    alu_op = ALU_AND;
                    ctrl_word[SIG_ALU_EN] = 1;
                    ctrl_word[SIG_A_LOAD] = 1;
                    stage_rst = 1;
                end
                OP_OR: begin
                    alu_op = ALU_OR;
                    ctrl_word[SIG_ALU_EN] = 1;
                    ctrl_word[SIG_A_LOAD] = 1;
                    stage_rst = 1;
                end
                OP_XOR: begin
                    alu_op = ALU_XOR;
                    ctrl_word[SIG_ALU_EN] = 1;
                    ctrl_word[SIG_A_LOAD] = 1;
                    stage_rst = 1;
                end
            endcase
        end
    endcase
end

assign out = ctrl_word;

endmodule

module alu(
    input clk,
    input[15:0] a,
    input[15:0] b,
    input[2:0] alu_op,
    input flag_c_in,
    output[15:0] out,
    output flag_c_out
);

localparam ALU_ADD = 0;
localparam ALU_ADDC = 1;
localparam ALU_SUB = 2;
localparam ALU_SUBB = 3;
localparam ALU_MOD = 4;
localparam ALU_AND = 5;
localparam ALU_OR = 6;
localparam ALU_XOR = 7;

reg flag_c_out;
reg[15:0] out;
always @(posedge clk) begin
    flag_c_out = flag_c_in;
    case (alu_op)
        ALU_ADD: begin
            {flag_c_out, out} = a + b;
        end
        ALU_ADDC: begin
            {flag_c_out, out} = a + b + flag_c_in;
        end
        ALU_SUB: begin
            {flag_c_out, out} = a - b;
        end
        ALU_SUBB: begin
            {flag_c_out, out} = a - b - flag_c_in;
        end
        ALU_MOD: begin
            out = a % b;
        end
        ALU_AND: begin
            out = a & b;
        end
        ALU_OR: begin
            out = a | b;
        end
        ALU_XOR: begin
            out = a ^ b;
        end
		default: begin
			out = 0;
		end
    endcase
end

endmodule

module a(
    input clk,
    input load,
    input[2:0] a_op,
    input[15:0] bus,
    input flag_c_in,
    output[15:0] out,
    output flag_c_out
);

//a ops
localparam A_INC = 1;
localparam A_DEC = 2;
localparam A_SHL = 3;
localparam A_SHR = 4;
localparam A_NOT = 5;
localparam A_COM = 6;

reg[15:0] a;
reg flag_c_out;

initial begin
    a = 16'b0;
end

always @(negedge clk) begin
    if (load) begin
        a <= bus;
    end else begin
        flag_c_out = flag_c_in;
        case (a_op)
            A_INC: begin
                {flag_c_out, a} = a + 1;
            end
            A_DEC: begin
                {flag_c_out, a} = a - 1;
            end
            A_SHL: begin
                flag_c_out = a[15];
                a = a << 1;
            end
            A_SHR: begin
                flag_c_out = a[0];
                a = a >> 1;
            end
            A_NOT: begin
                a = ~a;
            end
            A_COM: begin
                a = ~a + 1;
            end
        endcase
    end
end

assign out = a;

endmodule

module flag_mux(
    input clk,
    input[15:0] a_out,
    input alu_op,
    input a_load,
    input a_op,
    input alu_c_flag,
    input a_c_flag,
    output[2:0] out
);

localparam FLAG_Z = 0;
localparam FLAG_C = 1;
localparam FLAG_S = 2;

reg[2:0] flags;
reg load_from_alu;
reg load_from_a;

initial begin
    flags = 3'b001;
    load_from_a = 0;
    load_from_alu = 0;
end

always @(posedge clk) begin
    flags[FLAG_S] = a_out[15];
    flags[FLAG_Z] = (a_out == 0);

    if (alu_op) begin
        load_from_alu <= 1;
    end else if (a_op) begin
        load_from_a <= 1;
    end
    if (load_from_alu) begin
        flags[FLAG_C] <= alu_c_flag;
        load_from_alu = 0;
    end else if (load_from_a) begin
        flags[FLAG_C] <= a_c_flag;
        load_from_a = 0;
    end
end

assign out = flags;

endmodule

module register(
    input clk,
    input load,
    input[15:0] bus,
    output[15:0] out
);

reg[15:0] register;

always @(negedge clk) begin
    if (load) begin
        register <= bus;
    end
end

assign out = register;

endmodule

module pc(
    input clk,
    input load,
    input inc,
    input[11:0] bus,
    output[15:0] out
);

reg[11:0] register;
initial begin
    register = 12'b0;
end

always @(negedge clk) begin
    if (load) begin
        register <= bus;
    end else if (inc) begin
        register <= register + 1;
    end
end

assign out = {4'b0000, register};

endmodule

module sp(
    input clk,
    input stack_load,
    input sp_add,
    input[9:0] ram_arg,
    output[15:0] out
);

reg[11:0] register;

initial begin
    register <= 12'b111111111111;
end

always @(posedge clk) begin
    if (stack_load) begin
        register <= register - 1;
    end else if (sp_add) begin
        register <= register + ram_arg + 1;
    end
end

assign out = {4'b0000, register};

endmodule

cpu_tb.v
module cpu_tb();

reg CLK;

cpu cpu(CLK);

integer i;
initial begin
    $dumpfile("cpu.vcd");
    $dumpvars(0,cpu_tb);

    CLK = 1;
	for (i = 0; i < 2048; i++) begin
		#1 CLK = ~CLK;
	end

    $finish();
end

endmodule

cpu.vcd
$date
	Tue Sep 19 18:40:18 2023
$end
$version
	Icarus Verilog
$end
$timescale
	1s
$end
$scope module cpu_tb $end
$var reg 1 ! CLK $end
$var integer 32 " i [31:0] $end
$scope module cpu $end
$var wire 1 ! CLK $end
$var wire 1 # clk $end
$var wire 1 $ stack_load $end
$var wire 1 % stack_en $end
$var wire 16 & sp_out [15:0] $end
$var wire 1 ' sp_add $end
$var wire 16 ( ram_out [15:0] $end
$var wire 1 ) ram_load $end
$var wire 1 * ram_en $end
$var wire 16 + pc_out [15:0] $end
$var wire 1 , pc_load $end
$var wire 1 - pc_inc $end
$var wire 1 . pc_en $end
$var wire 1 / mar_load $end
$var wire 16 0 ir_out [15:0] $end
$var wire 1 1 ir_load $end
$var wire 1 2 ir_en $end
$var wire 3 3 flags [2:0] $end
$var wire 16 4 b_out [15:0] $end
$var wire 1 5 b_load $end
$var wire 1 6 b_en $end
$var wire 16 7 alu_out [15:0] $end
$var wire 3 8 alu_op [2:0] $end
$var wire 1 9 alu_en $end
$var wire 1 : alu_c_flag $end
$var wire 16 ; a_out [15:0] $end
$var wire 3 < a_op [2:0] $end
$var wire 1 = a_load $end
$var wire 1 > a_en $end
$var wire 1 ? a_c_flag $end
$var reg 16 @ bus [15:0] $end
$scope module alu $end
$var wire 1 # clk $end
$var wire 1 A flag_c_in $end
$var wire 16 B b [15:0] $end
$var wire 3 C alu_op [2:0] $end
$var wire 16 D a [15:0] $end
$var reg 1 : flag_c_out $end
$var reg 16 E out [15:0] $end
$upscope $end
$scope module controller $end
$var wire 1 # clk $end
$var wire 4 F ir_opcode [3:0] $end
$var wire 16 G out [15:0] $end
$var wire 12 H ram_arg [11:0] $end
$var wire 4 I ram_opcode [3:0] $end
$var wire 2 J stack_opcode [1:0] $end
$var wire 2 K ram_stack_opcode [1:0] $end
$var wire 3 L flags [2:0] $end
$var reg 3 M a_op [2:0] $end
$var reg 3 N alu_op [2:0] $end
$var reg 16 O ctrl_word [15:0] $end
$var reg 3 P stage [2:0] $end
$var reg 1 Q stage_rst $end
$upscope $end
$scope module flag_mux $end
$var wire 1 = a_load $end
$var wire 1 R a_op $end
$var wire 1 : alu_c_flag $end
$var wire 1 S alu_op $end
$var wire 1 # clk $end
$var wire 3 T out [2:0] $end
$var wire 16 U a_out [15:0] $end
$var wire 1 ? a_c_flag $end
$var reg 3 V flags [2:0] $end
$var reg 1 W load_from_a $end
$var reg 1 X load_from_alu $end
$upscope $end
$scope module ir $end
$var wire 16 Y bus [15:0] $end
$var wire 1 # clk $end
$var wire 1 1 load $end
$var wire 16 Z out [15:0] $end
$var reg 16 [ register [15:0] $end
$upscope $end
$scope module pc $end
$var wire 12 \ bus [11:0] $end
$var wire 1 # clk $end
$var wire 1 - inc $end
$var wire 1 , load $end
$var wire 16 ] out [15:0] $end
$var reg 12 ^ register [11:0] $end
$upscope $end
$scope module ram $end
$var wire 16 _ bus [15:0] $end
$var wire 1 # clk $end
$var wire 10 ` ir_arg [9:0] $end
$var wire 1 / mar_load $end
$var wire 1 * ram_en $end
$var wire 1 ) ram_load $end
$var wire 1 % stack_en $end
$var wire 1 $ stack_load $end
$var wire 17 a top [16:0] $end
$var wire 16 b sp_out [15:0] $end
$var reg 12 c mar [11:0] $end
$var reg 16 d out [15:0] $end
$var integer 32 e i [31:0] $end
$upscope $end
$scope module reg_a $end
$var wire 3 f a_op [2:0] $end
$var wire 16 g bus [15:0] $end
$var wire 1 # clk $end
$var wire 1 h flag_c_in $end
$var wire 1 = load $end
$var wire 16 i out [15:0] $end
$var reg 16 j a [15:0] $end
$var reg 1 ? flag_c_out $end
$upscope $end
$scope module reg_b $end
$var wire 16 k bus [15:0] $end
$var wire 1 # clk $end
$var wire 1 5 load $end
$var wire 16 l out [15:0] $end
$var reg 16 m register [15:0] $end
$upscope $end
$scope module sp $end
$var wire 1 # clk $end
$var wire 10 n ram_arg [9:0] $end
$var wire 1 ' sp_add $end
$var wire 1 $ stack_load $end
$var wire 16 o out [15:0] $end
$var reg 12 p register [11:0] $end
$upscope $end
$upscope $end
$upscope $end
$enddefinitions $end
#0
$dumpvars
b111111111111 p
b111111111111 o
bx n
bx m
bx l
b0 k
b0 j
b0 i
0h
b0 g
b0 f
b1000000000000 e
bx d
b0 c
b111111111111 b
b0 a
bx `
b0 _
b0 ^
b0 ]
b0 \
bx [
bx Z
b0 Y
0X
0W
b1 V
b0 U
b1 T
0S
0R
0Q
b0 P
b10000010000 O
b0 N
b0 M
b1 L
bx K
bx J
bx I
bx H
b10000010000 G
bx F
bx E
b0 D
b0 C
bx B
0A
b0 @
x?
0>
0=
b0 <
b0 ;
x:
09
b0 8
bx 7
06
05
bx 4
b1 3
02
01
bx 0
1/
1.
0-
0,
b0 +
0*
0)
bx (
0'
b111111111111 &
0%
0$
1#
b0 "
1!
$end
#1
bx \
bx @
bx Y
bx _
bx g
bx k
1-
11
1*
0.
0/
b100000000101 G
b100000000101 O
b1 P
0?
b1 "
0#
0!
#2
b0 K
b100000000101 G
b100000000101 O
b10 \
b10 n
b10 H
b1111 I
b1111000000000010 @
b1111000000000010 Y
b1111000000000010 _
b1111000000000010 g
b1111000000000010 k
b1111000000000010 (
b1111000000000010 d
x:
b10 "
1#
1!
#3
1,
1$
01
0-
b0 J
b1111 F
b10 `
1Q
b1000100000001000 G
b1000100000001000 O
b1 +
b1 ]
b1 ^
b1111000000000010 0
b1111000000000010 Z
b1111000000000010 [
b10 P
b11 "
0#
0!
#4
b111111111110 &
b111111111110 b
b111111111110 o
b111111111110 p
x:
b100 "
1#
1!
#5
b10 @
b10 Y
b10 _
b10 g
b10 k
1/
1.
0,
0*
0$
0Q
b10000010000 G
b10000010000 O
b0 P
b10 +
b10 ]
b10 ^
b101 "
0#
0!
#6
b10 c
x:
b110 "
1#
1!
#7
b1111000000000010 @
b1111000000000010 Y
b1111000000000010 _
b1111000000000010 g
b1111000000000010 k
1-
11
1*
0.
0/
b100000000101 G
b100000000101 O
b1 P
b111 "
0#
0!
#8
1Q
1R
b1 <
b1 M
b1 f
b100000000101 G
b100000000101 O
b1 \
b1 n
b1 H
b0 I
b1 @
b1 Y
b1 _
b1 g
b1 k
b1 (
b1 d
x:
b1000 "
1#
1!
#9
b11 \
b11 @
b11 Y
b11 _
b11 g
b11 k
1/
1.
01
0-
0*
0Q
0R
b0 <
b0 M
b0 f
b10000010000 G
b10000010000 O
b0 F
b1 `
b0 P
b1 0
b1 Z
b1 [
b11 +
b11 ]
b11 ^
b1 ;
b1 D
b1 U
b1 i
b1 j
b1001 "
0#
0!
#10
b11 c
b10000010000 G
b10000010000 O
b0 3
b0 L
b0 T
b0 V
x:
b1010 "
1#
1!
#11
b1 \
b1 @
b1 Y
b1 _
b1 g
b1 k
1-
11
1*
0.
0/
1Q
1R
b1 <
b1 M
b1 f
b100000000101 G
b100000000101 O
b1 P
b1011 "
0#
0!
#12
0Q
0R
b0 <
b0 M
b0 f
b100000000101 G
b100000000101 O
b11 K
b110000000000 \
b0 n
b110000000000 H
b110000000000 @
b110000000000 Y
b110000000000 _
b110000000000 g
b110000000000 k
1W
b110000000000 (
b110000000000 d
x:
b1100 "
1#
1!
#13
1'
1,
1%
01
0-
0*
1Q
b110000000001000 G
b110000000001000 O
b11 J
b0 `
b10 P
b110000000000 0
b110000000000 Z
b110000000000 [
b100 +
b100 ]
b100 ^
b1101 "
0#
0!
#14
1Q
b110000000001000 G
b110000000001000 O
b0 K
b0 \
b0 H
b0 @
b0 Y
b0 _
b0 g
b0 k
b111111111111 &
b111111111111 b
b111111111111 o
b111111111111 p
b0 (
b0 d
0W
x:
b1110 "
1#
1!
#15
1/
1.
0,
0'
0%
0Q
b10000010000 G
b10000010000 O
b0 +
b0 ]
b0 ^
b0 P
b1111 "
0#
0!
#16
b0 c
x:
b10000 "
1#
1!
#17
1-
11
1*
0.
0/
1Q
b100000000101 G
b100000000101 O
b1 P
b10001 "
0#
0!
#18
0Q
b100000000101 G
b100000000101 O
b10 \
b10 n
b10 H
b1111 I
b1111000000000010 @
b1111000000000010 Y
b1111000000000010 _
b1111000000000010 g
b1111000000000010 k
b1111000000000010 (
b1111000000000010 d
x:
b10010 "
1#
1!
#19
1,
1$
01
0-
b0 J
b1111 F
b10 `
1Q
b1000100000001000 G
b1000100000001000 O
b1 +
b1 ]
b1 ^
b1111000000000010 0
b1111000000000010 Z
b1111000000000010 [
b10 P
b10011 "
0#
0!
#20
b111111111110 &
b111111111110 b
b111111111110 o
b111111111110 p
x:
b10100 "
1#
1!
#21
b10 @
b10 Y
b10 _
b10 g
b10 k
1/
1.
0,
0*
0$
0Q
b10000010000 G
b10000010000 O
b0 P
b10 +
b10 ]
b10 ^
b10101 "
0#
0!
#22
b10 c
x:
b10110 "
1#
1!
#23
b1111000000000010 @
b1111000000000010 Y
b1111000000000010 _
b1111000000000010 g
b1111000000000010 k
1-
11
1*
0.
0/
b100000000101 G
b100000000101 O
b1 P
b10111 "
0#
0!
#24
1Q
1R
b1 <
b1 M
b1 f
b100000000101 G
b100000000101 O
b1 \
b1 n
b1 H
b0 I
b1 @
b1 Y
b1 _
b1 g
b1 k
b1 (
b1 d
x:
b11000 "
1#
1!
#25
b11 \
b11 @
b11 Y
b11 _
b11 g
b11 k
1/
1.
01
0-
0*
0Q
0R
b0 <
b0 M
b0 f
b10000010000 G
b10000010000 O
b0 F
b1 `
b0 P
b1 0
b1 Z
b1 [
b11 +
b11 ]
b11 ^
b10 ;
b10 D
b10 U
b10 i
b10 j
b11001 "
0#
0!
#26
b11 c
x:
b11010 "
1#
1!
#27
b1 \
b1 @
b1 Y
b1 _
b1 g
b1 k
1-
11
1*
0.
0/
1Q
1R
b1 <
b1 M
b1 f
b100000000101 G
b100000000101 O
b1 P
b11011 "
0#
0!
#28
0Q
0R
b0 <
b0 M
b0 f
b100000000101 G
b100000000101 O
b11 K
b110000000000 \
b0 n
b110000000000 H
b110000000000 @
b110000000000 Y
b110000000000 _
b110000000000 g
b110000000000 k
1W
b110000000000 (
b110000000000 d
x:
b11100 "
1#
1!
#29
1'
1,
1%
01
0-
0*
1Q
b110000000001000 G
b110000000001000 O
b11 J
b0 `
b10 P
b110000000000 0
b110000000000 Z
b110000000000 [
b100 +
b100 ]
b100 ^
b11101 "
0#
0!
#30
1Q
b110000000001000 G
b110000000001000 O
b0 K
b0 \
b0 H
b0 @
b0 Y
b0 _
b0 g
b0 k
b111111111111 &
b111111111111 b
b111111111111 o
b111111111111 p
b0 (
b0 d
0W
x:
b11110 "
1#
1!
#31
1/
1.
0,
0'
0%
0Q
b10000010000 G
b10000010000 O
b0 +
b0 ]
b0 ^
b0 P
b11111 "
0#
0!
#32
b0 c
x:
b100000 "
1#
1!
#33
1-
11
1*
0.
0/
1Q
b100000000101 G
b100000000101 O
b1 P
b100001 "
0#
0!
#34
0Q
b100000000101 G
b100000000101 O
b10 \
b10 n
b10 H
b1111 I
b1111000000000010 @
b1111000000000010 Y
b1111000000000010 _
b1111000000000010 g
b1111000000000010 k
b1111000000000010 (
b1111000000000010 d
x:
b100010 "
1#
1!
#35
1,
1$
01
0-
b0 J
b1111 F
b10 `
1Q
b1000100000001000 G
b1000100000001000 O
b1 +
b1 ]
b1 ^
b1111000000000010 0
b1111000000000010 Z
b1111000000000010 [
b10 P
b100011 "
0#
0!
#36
b111111111110 &
b111111111110 b
b111111111110 o
b111111111110 p
x:
b100100 "
1#
1!
#37
b10 @
b10 Y
b10 _
b10 g
b10 k
1/
1.
0,
0*
0$
0Q
b10000010000 G
b10000010000 O
b0 P
b10 +
b10 ]
b10 ^
b100101 "
0#
0!
#38
b10 c
x:
b100110 "
1#
1!
#39
b1111000000000010 @
b1111000000000010 Y
b1111000000000010 _
b1111000000000010 g
b1111000000000010 k
1-
11
1*
0.
0/
b100000000101 G
b100000000101 O
b1 P
b100111 "
0#
0!
